MANIFEST.in
README
setup.cfg
setup.py
pyqdbm.egg-info/PKG-INFO
pyqdbm.egg-info/SOURCES.txt
pyqdbm.egg-info/dependency_links.txt
pyqdbm.egg-info/top_level.txt
qdbm/__init__.py
src/depot2.c
src/depot3.c