Metadata-Version: 1.0
Name: pyqdbm
Version: 0.9.6
Summary: Python binding for QDBM Database
Home-page: https://www.hirano.cc/pyqdbm
Author: HIRANO Yoshitaka
Author-email: yo@hirano.cc
License: MIT
Keywords: QDBM
Platform: UNKNOWN
